CHANGES.rst
DESCRIPTION.rst
LICENSE
MANIFEST.in
README.md
setup.py
src/sfp/__init__.py
src/sfp/_poller.py
src/simple_file_poller.egg-info/PKG-INFO
src/simple_file_poller.egg-info/SOURCES.txt
src/simple_file_poller.egg-info/dependency_links.txt
src/simple_file_poller.egg-info/requires.txt
src/simple_file_poller.egg-info/top_level.txt