Metadata-Version: 2.1
Name: simple-file-poller
Version: 0.0.13
Summary: Simple Python 3 library for file polling.
Home-page: https://github.com/waikato-datamining/simple-file-poller
Author: Peter Reutemann
Author-email: fracpete@waikato.ac.nz
License: MIT License
Classifier: Development Status :: 4 - Beta
Classifier: License :: OSI Approved :: MIT License
Classifier: Topic :: System :: Filesystems
Classifier: Programming Language :: Python :: 3
License-File: LICENSE
